{
    "summit_therapy": {
        "client_id": "summit_therapy",
        "name": "Summit Therapy",
        "services": {
            "website_build": true,
            "care_plan": true,
            "seo": false,
            "gbp_management": false,
            "gbp_posts_per_month": 8,
            "blog": false,
            "blog_posts_per_month": 0,
            "social_media": false,
            "social_posts_per_month": 8,
            "linkedin_posts_per_month": 2,
            "newsletter": false,
            "paid_ads": false
        },
        "vertical": [
            "speech_pathology",
            "occupational_therapy",
            "physical_therapy"
        ],
        "intake_submission_ids": [
            "33bf7f45-333e-81e3-b962-dc5f7d5873ca",
            "33bf7f45-333e-8194-9159-ef1692d9fea2"
        ],
        "client_info_db_id": "33bf7f45-333e-8183-8ecc-cfcfa7386ce9",
        "client_log_db_id": "343f7f45-333e-81cb-a3c0-f74302995a9b",
        "brand_guidelines_db_id": "33bf7f45-333e-8178-b83d-dca28ae7a1ef",
        "care_plan_db_id": "33ef7f45-333e-8187-ba68-efc21a3f904b",
        "business_profile_page_id": "343f7f45-333e-818a-81b0-d94ac08f1bfb",
        "sitemap_db_id": "33bf7f45-333e-8195-bb5e-e3169f1ad300",
        "content_db_id": "33bf7f45-333e-81cd-ab1c-f6aa9d13bbb0",
        "images_db_id": "33bf7f45-333e-8136-8d61-e281fb412ba0",
        "competitors_db_id": "33ef7f45-333e-81ba-acc8-dd0ca90d2493",
        "keywords_db_id": "33ef7f45-333e-81ba-a3c8-c681dcd9965a",
        "seo_metrics_db_id": "",
        "gbp_posts_db_id": "341f7f45-333e-81f9-bb71-e97b4b8358a2",
        "blog_posts_db_id": "",
        "social_posts_db_id": "",
        "gbp_location_id": "",
        "clickup_review_list_id": "",
        "meeting_notes_entry_id": "33bf7f45-333e-81d2-8842-d50e795d681e",
        "meeting_notes_db_id": "33bf7f45-333e-81ec-ab37-f0b0beaa115a"
    },
    "cielo_treatment_center": {
        "client_id": "cielo_treatment_center",
        "name": "Cielo Treatment Center",
        "services": {
            "website_build": false,
            "care_plan": true,
            "seo": true,
            "gbp_management": true,
            "gbp_posts_per_month": 8,
            "blog": true,
            "blog_posts_per_month": 4,
            "social_media": true,
            "social_posts_per_month": 8,
            "linkedin_posts_per_month": 2,
            "newsletter": true,
            "paid_ads": true
        },
        "vertical": [
            "addiction_treatment"
        ],
        "client_info_db_id": "343f7f45-333e-815c-bce4-cb761f1af547",
        "client_log_db_id": "343f7f45-333e-81a4-b482-e60b4598de39",
        "brand_guidelines_db_id": "343f7f45-333e-813e-942d-f4c264ad957b",
        "care_plan_db_id": "343f7f45-333e-819d-92e8-c28ba6df40c6",
        "business_profile_page_id": "343f7f45-333e-8126-b17b-ee8800ada596",
        "sitemap_db_id": "",
        "content_db_id": "",
        "images_db_id": "",
        "competitors_db_id": "343f7f45-333e-81e7-8951-dcfd418cb20a",
        "keywords_db_id": "343f7f45-333e-8139-a77c-e7ce503961df",
        "seo_metrics_db_id": "",
        "gbp_posts_db_id": "",
        "blog_posts_db_id": "",
        "social_posts_db_id": "",
        "gbp_location_id": "",
        "clickup_review_list_id": "",
        "migration_source": "google_drive"
    },
    "another_chance": {
        "client_id": "another_chance",
        "name": "Another Chance",
        "services": {
            "website_build": true,
            "care_plan": true,
            "seo": true,
            "gbp_management": true,
            "gbp_posts_per_month": 8,
            "blog": true,
            "blog_posts_per_month": 4,
            "social_media": true,
            "social_posts_per_month": 8,
            "linkedin_posts_per_month": 2,
            "newsletter": true,
            "paid_ads": false
        },
        "vertical": [
            "addiction_treatment"
        ],
        "client_info_db_id": "343f7f45-333e-8183-a385-e2932859bd84",
        "client_log_db_id": "343f7f45-333e-81ae-b9ff-e30960e9e3fa",
        "brand_guidelines_db_id": "343f7f45-333e-81ed-a02d-c48aac5a73de",
        "care_plan_db_id": "343f7f45-333e-81b7-a04d-d7acad81e79c",
        "business_profile_page_id": "343f7f45-333e-812b-9993-c19ad6b28f91",
        "sitemap_db_id": "343f7f45-333e-81c4-b9bc-ce6c80192ddd",
        "content_db_id": "343f7f45-333e-81eb-b289-ec47b92abcc2",
        "images_db_id": "343f7f45-333e-810d-9d8f-e8780dd4f6d6",
        "competitors_db_id": "343f7f45-333e-81aa-804b-c792b36cf253",
        "keywords_db_id": "343f7f45-333e-8152-86ff-d0a5905ac155",
        "seo_metrics_db_id": "",
        "gbp_posts_db_id": "",
        "blog_posts_db_id": "",
        "social_posts_db_id": "",
        "gbp_location_id": "",
        "clickup_review_list_id": "",
        "migration_source": "google_drive"
    },
    "lotus_recovery": {
        "client_id": "lotus_recovery",
        "name": "Lotus Recovery",
        "services": {
            "website_build": true,
            "care_plan": true,
            "seo": true,
            "gbp_management": true,
            "gbp_posts_per_month": 8,
            "blog": true,
            "blog_posts_per_month": 4,
            "social_media": true,
            "social_posts_per_month": 8,
            "linkedin_posts_per_month": 2,
            "newsletter": false,
            "paid_ads": true
        },
        "vertical": [
            "addiction_treatment"
        ],
        "client_info_db_id": "343f7f45-333e-81b4-813e-f98d183d98ab",
        "client_log_db_id": "343f7f45-333e-8139-bcd8-fc4a6dabbcf8",
        "brand_guidelines_db_id": "343f7f45-333e-8187-bb6c-de2cb5778c5f",
        "care_plan_db_id": "343f7f45-333e-819f-8bcb-d17395660435",
        "business_profile_page_id": "343f7f45-333e-81c3-a3f3-da3756bbdf73",
        "sitemap_db_id": "343f7f45-333e-813d-bc00-da29c63e6642",
        "content_db_id": "343f7f45-333e-81e9-8ab9-c792faf6d6a0",
        "images_db_id": "343f7f45-333e-816c-ad64-e720bb2c9eab",
        "competitors_db_id": "343f7f45-333e-8130-8f04-c78abf89aae0",
        "keywords_db_id": "343f7f45-333e-8140-86d4-ea47885b3458",
        "seo_metrics_db_id": "",
        "gbp_posts_db_id": "",
        "blog_posts_db_id": "",
        "social_posts_db_id": "",
        "gbp_location_id": "",
        "clickup_review_list_id": "",
        "migration_source": "google_drive"
    }
}